[
    {
        "drum_type": "hi-hat",
        "onset_time_seconds": 0.0,
        "midi_pitch": 42,
        "note_head_type": "x",
        "staff_position": "F#3",
        "display_name": "Hi-Hat (Closed)"
    },
    {
        "drum_type": "hi-hat",
        "onset_time_seconds": 0.1,
        "midi_pitch": 42,
        "note_head_type": "x",
        "staff_position": "F#3",
        "display_name": "Hi-Hat (Closed)"
    },
    {
        "drum_type": "snare",
        "onset_time_seconds": 0.3,
        "midi_pitch": 38,
        "note_head_type": "normal",
        "staff_position": "C3",
        "display_name": "Snare Drum"
    },
    {
        "drum_type": "hi-hat",
        "onset_time_seconds": 0.4,
        "midi_pitch": 42,
        "note_head_type": "x",
        "staff_position": "F#3",
        "display_name": "Hi-Hat (Closed)"
    },
    {
        "drum_type": "hi-hat",
        "onset_time_seconds": 0.5,
        "midi_pitch": 42,
        "note_head_type": "x",
        "staff_position": "F#3",
        "display_name": "Hi-Hat (Closed)"
    },
    {
        "drum_type": "hi-hat",
        "onset_time_seconds": 0.6,
        "midi_pitch": 42,
        "note_head_type": "x",
        "staff_position": "F#3",
        "display_name": "Hi-Hat (Closed)"
    },
    {
        "drum_type": "hi-hat",
        "onset_time_seconds": 0.7,
        "midi_pitch": 42,
        "note_head_type": "x",
        "staff_position": "F#3",
        "display_name": "Hi-Hat (Closed)"
    },
    {
        "drum_type": "hi-hat",
        "onset_time_seconds": 0.8,
        "midi_pitch": 42,
        "note_head_type": "x",
        "staff_position": "F#3",
        "display_name": "Hi-Hat (Closed)"
    },
    {
        "drum_type": "snare",
        "onset_time_seconds": 0.9,
        "midi_pitch": 38,
        "note_head_type": "normal",
        "staff_position": "C3",
        "display_name": "Snare Drum"
    },
    {
        "drum_type": "snare",
        "onset_time_seconds": 1.1,
        "midi_pitch": 38,
        "note_head_type": "normal",
        "staff_position": "C3",
        "display_name": "Snare Drum"
    },
    {
        "drum_type": "snare",
        "onset_time_seconds": 1.2,
        "midi_pitch": 38,
        "note_head_type": "normal",
        "staff_position": "C3",
        "display_name": "Snare Drum"
    },
    {
        "drum_type": "hi-hat",
        "onset_time_seconds": 1.4,
        "midi_pitch": 42,
        "note_head_type": "x",
        "staff_position": "F#3",
        "display_name": "Hi-Hat (Closed)"
    },
    {
        "drum_type": "hi-hat",
        "onset_time_seconds": 1.9,
        "midi_pitch": 42,
        "note_head_type": "x",
        "staff_position": "F#3",
        "display_name": "Hi-Hat (Closed)"
    },
    {
        "drum_type": "hi-hat",
        "onset_time_seconds": 2.0,
        "midi_pitch": 42,
        "note_head_type": "x",
        "staff_position": "F#3",
        "display_name": "Hi-Hat (Closed)"
    },
    {
        "drum_type": "snare",
        "onset_time_seconds": 2.1,
        "midi_pitch": 38,
        "note_head_type": "normal",
        "staff_position": "C3",
        "display_name": "Snare Drum"
    },
    {
        "drum_type": "hi-hat",
        "onset_time_seconds": 2.3,
        "midi_pitch": 42,
        "note_head_type": "x",
        "staff_position": "F#3",
        "display_name": "Hi-Hat (Closed)"
    },
    {
        "drum_type": "hi-hat",
        "onset_time_seconds": 2.4,
        "midi_pitch": 42,
        "note_head_type": "x",
        "staff_position": "F#3",
        "display_name": "Hi-Hat (Closed)"
    },
    {
        "drum_type": "hi-hat",
        "onset_time_seconds": 2.5,
        "midi_pitch": 42,
        "note_head_type": "x",
        "staff_position": "F#3",
        "display_name": "Hi-Hat (Closed)"
    },
    {
        "drum_type": "hi-hat",
        "onset_time_seconds": 2.6,
        "midi_pitch": 42,
        "note_head_type": "x",
        "staff_position": "F#3",
        "display_name": "Hi-Hat (Closed)"
    },
    {
        "drum_type": "snare",
        "onset_time_seconds": 2.8,
        "midi_pitch": 38,
        "note_head_type": "normal",
        "staff_position": "C3",
        "display_name": "Snare Drum"
    },
    {
        "drum_type": "hi-hat",
        "onset_time_seconds": 3.1,
        "midi_pitch": 42,
        "note_head_type": "x",
        "staff_position": "F#3",
        "display_name": "Hi-Hat (Closed)"
    },
    {
        "drum_type": "hi-hat",
        "onset_time_seconds": 3.2,
        "midi_pitch": 42,
        "note_head_type": "x",
        "staff_position": "F#3",
        "display_name": "Hi-Hat (Closed)"
    },
    {
        "drum_type": "hi-hat",
        "onset_time_seconds": 3.3,
        "midi_pitch": 42,
        "note_head_type": "x",
        "staff_position": "F#3",
        "display_name": "Hi-Hat (Closed)"
    },
    {
        "drum_type": "hi-hat",
        "onset_time_seconds": 3.4,
        "midi_pitch": 42,
        "note_head_type": "x",
        "staff_position": "F#3",
        "display_name": "Hi-Hat (Closed)"
    },
    {
        "drum_type": "hi-hat",
        "onset_time_seconds": 3.5,
        "midi_pitch": 42,
        "note_head_type": "x",
        "staff_position": "F#3",
        "display_name": "Hi-Hat (Closed)"
    },
    {
        "drum_type": "hi-hat",
        "onset_time_seconds": 3.6,
        "midi_pitch": 42,
        "note_head_type": "x",
        "staff_position": "F#3",
        "display_name": "Hi-Hat (Closed)"
    },
    {
        "drum_type": "hi-hat",
        "onset_time_seconds": 3.7,
        "midi_pitch": 42,
        "note_head_type": "x",
        "staff_position": "F#3",
        "display_name": "Hi-Hat (Closed)"
    },
    {
        "drum_type": "hi-hat",
        "onset_time_seconds": 3.8,
        "midi_pitch": 42,
        "note_head_type": "x",
        "staff_position": "F#3",
        "display_name": "Hi-Hat (Closed)"
    },
    {
        "drum_type": "hi-hat",
        "onset_time_seconds": 3.9,
        "midi_pitch": 42,
        "note_head_type": "x",
        "staff_position": "F#3",
        "display_name": "Hi-Hat (Closed)"
    },
    {
        "drum_type": "snare",
        "onset_time_seconds": 4.0,
        "midi_pitch": 38,
        "note_head_type": "normal",
        "staff_position": "C3",
        "display_name": "Snare Drum"
    },
    {
        "drum_type": "hi-hat",
        "onset_time_seconds": 4.1,
        "midi_pitch": 42,
        "note_head_type": "x",
        "staff_position": "F#3",
        "display_name": "Hi-Hat (Closed)"
    },
    {
        "drum_type": "hi-hat",
        "onset_time_seconds": 4.2,
        "midi_pitch": 42,
        "note_head_type": "x",
        "staff_position": "F#3",
        "display_name": "Hi-Hat (Closed)"
    },
    {
        "drum_type": "hi-hat",
        "onset_time_seconds": 4.3,
        "midi_pitch": 42,
        "note_head_type": "x",
        "staff_position": "F#3",
        "display_name": "Hi-Hat (Closed)"
    },
    {
        "drum_type": "hi-hat",
        "onset_time_seconds": 4.4,
        "midi_pitch": 42,
        "note_head_type": "x",
        "staff_position": "F#3",
        "display_name": "Hi-Hat (Closed)"
    },
    {
        "drum_type": "hi-hat",
        "onset_time_seconds": 4.5,
        "midi_pitch": 42,
        "note_head_type": "x",
        "staff_position": "F#3",
        "display_name": "Hi-Hat (Closed)"
    },
    {
        "drum_type": "snare",
        "onset_time_seconds": 4.8,
        "midi_pitch": 38,
        "note_head_type": "normal",
        "staff_position": "C3",
        "display_name": "Snare Drum"
    },
    {
        "drum_type": "snare",
        "onset_time_seconds": 4.9,
        "midi_pitch": 38,
        "note_head_type": "normal",
        "staff_position": "C3",
        "display_name": "Snare Drum"
    },
    {
        "drum_type": "hi-hat",
        "onset_time_seconds": 5.0,
        "midi_pitch": 42,
        "note_head_type": "x",
        "staff_position": "F#3",
        "display_name": "Hi-Hat (Closed)"
    },
    {
        "drum_type": "hi-hat",
        "onset_time_seconds": 5.1,
        "midi_pitch": 42,
        "note_head_type": "x",
        "staff_position": "F#3",
        "display_name": "Hi-Hat (Closed)"
    },
    {
        "drum_type": "kick",
        "onset_time_seconds": 5.2,
        "midi_pitch": 36,
        "note_head_type": "normal",
        "staff_position": "F2",
        "display_name": "Bass Drum"
    },
    {
        "drum_type": "hi-hat",
        "onset_time_seconds": 5.6,
        "midi_pitch": 42,
        "note_head_type": "x",
        "staff_position": "F#3",
        "display_name": "Hi-Hat (Closed)"
    },
    {
        "drum_type": "snare",
        "onset_time_seconds": 5.8,
        "midi_pitch": 38,
        "note_head_type": "normal",
        "staff_position": "C3",
        "display_name": "Snare Drum"
    },
    {
        "drum_type": "hi-hat",
        "onset_time_seconds": 5.9,
        "midi_pitch": 42,
        "note_head_type": "x",
        "staff_position": "F#3",
        "display_name": "Hi-Hat (Closed)"
    },
    {
        "drum_type": "hi-hat",
        "onset_time_seconds": 6.0,
        "midi_pitch": 42,
        "note_head_type": "x",
        "staff_position": "F#3",
        "display_name": "Hi-Hat (Closed)"
    },
    {
        "drum_type": "snare",
        "onset_time_seconds": 6.1,
        "midi_pitch": 38,
        "note_head_type": "normal",
        "staff_position": "C3",
        "display_name": "Snare Drum"
    },
    {
        "drum_type": "hi-hat",
        "onset_time_seconds": 6.3,
        "midi_pitch": 42,
        "note_head_type": "x",
        "staff_position": "F#3",
        "display_name": "Hi-Hat (Closed)"
    },
    {
        "drum_type": "snare",
        "onset_time_seconds": 6.4,
        "midi_pitch": 38,
        "note_head_type": "normal",
        "staff_position": "C3",
        "display_name": "Snare Drum"
    },
    {
        "drum_type": "snare",
        "onset_time_seconds": 6.5,
        "midi_pitch": 38,
        "note_head_type": "normal",
        "staff_position": "C3",
        "display_name": "Snare Drum"
    },
    {
        "drum_type": "hi-hat",
        "onset_time_seconds": 6.8,
        "midi_pitch": 42,
        "note_head_type": "x",
        "staff_position": "F#3",
        "display_name": "Hi-Hat (Closed)"
    },
    {
        "drum_type": "hi-hat",
        "onset_time_seconds": 7.0,
        "midi_pitch": 42,
        "note_head_type": "x",
        "staff_position": "F#3",
        "display_name": "Hi-Hat (Closed)"
    },
    {
        "drum_type": "hi-hat",
        "onset_time_seconds": 7.1,
        "midi_pitch": 42,
        "note_head_type": "x",
        "staff_position": "F#3",
        "display_name": "Hi-Hat (Closed)"
    },
    {
        "drum_type": "hi-hat",
        "onset_time_seconds": 7.2,
        "midi_pitch": 42,
        "note_head_type": "x",
        "staff_position": "F#3",
        "display_name": "Hi-Hat (Closed)"
    },
    {
        "drum_type": "hi-hat",
        "onset_time_seconds": 7.4,
        "midi_pitch": 42,
        "note_head_type": "x",
        "staff_position": "F#3",
        "display_name": "Hi-Hat (Closed)"
    },
    {
        "drum_type": "hi-hat",
        "onset_time_seconds": 7.8,
        "midi_pitch": 42,
        "note_head_type": "x",
        "staff_position": "F#3",
        "display_name": "Hi-Hat (Closed)"
    },
    {
        "drum_type": "hi-hat",
        "onset_time_seconds": 7.9,
        "midi_pitch": 42,
        "note_head_type": "x",
        "staff_position": "F#3",
        "display_name": "Hi-Hat (Closed)"
    },
    {
        "drum_type": "hi-hat",
        "onset_time_seconds": 8.0,
        "midi_pitch": 42,
        "note_head_type": "x",
        "staff_position": "F#3",
        "display_name": "Hi-Hat (Closed)"
    },
    {
        "drum_type": "hi-hat",
        "onset_time_seconds": 8.1,
        "midi_pitch": 42,
        "note_head_type": "x",
        "staff_position": "F#3",
        "display_name": "Hi-Hat (Closed)"
    },
    {
        "drum_type": "hi-hat",
        "onset_time_seconds": 8.2,
        "midi_pitch": 42,
        "note_head_type": "x",
        "staff_position": "F#3",
        "display_name": "Hi-Hat (Closed)"
    },
    {
        "drum_type": "snare",
        "onset_time_seconds": 8.5,
        "midi_pitch": 38,
        "note_head_type": "normal",
        "staff_position": "C3",
        "display_name": "Snare Drum"
    },
    {
        "drum_type": "snare",
        "onset_time_seconds": 8.6,
        "midi_pitch": 38,
        "note_head_type": "normal",
        "staff_position": "C3",
        "display_name": "Snare Drum"
    },
    {
        "drum_type": "hi-hat",
        "onset_time_seconds": 8.8,
        "midi_pitch": 42,
        "note_head_type": "x",
        "staff_position": "F#3",
        "display_name": "Hi-Hat (Closed)"
    },
    {
        "drum_type": "hi-hat",
        "onset_time_seconds": 8.9,
        "midi_pitch": 42,
        "note_head_type": "x",
        "staff_position": "F#3",
        "display_name": "Hi-Hat (Closed)"
    },
    {
        "drum_type": "kick",
        "onset_time_seconds": 9.1,
        "midi_pitch": 36,
        "note_head_type": "normal",
        "staff_position": "F2",
        "display_name": "Bass Drum"
    },
    {
        "drum_type": "kick",
        "onset_time_seconds": 9.2,
        "midi_pitch": 36,
        "note_head_type": "normal",
        "staff_position": "F2",
        "display_name": "Bass Drum"
    },
    {
        "drum_type": "hi-hat",
        "onset_time_seconds": 9.3,
        "midi_pitch": 42,
        "note_head_type": "x",
        "staff_position": "F#3",
        "display_name": "Hi-Hat (Closed)"
    },
    {
        "drum_type": "hi-hat",
        "onset_time_seconds": 9.4,
        "midi_pitch": 42,
        "note_head_type": "x",
        "staff_position": "F#3",
        "display_name": "Hi-Hat (Closed)"
    },
    {
        "drum_type": "snare",
        "onset_time_seconds": 9.5,
        "midi_pitch": 38,
        "note_head_type": "normal",
        "staff_position": "C3",
        "display_name": "Snare Drum"
    },
    {
        "drum_type": "hi-hat",
        "onset_time_seconds": 9.7,
        "midi_pitch": 42,
        "note_head_type": "x",
        "staff_position": "F#3",
        "display_name": "Hi-Hat (Closed)"
    },
    {
        "drum_type": "hi-hat",
        "onset_time_seconds": 9.8,
        "midi_pitch": 42,
        "note_head_type": "x",
        "staff_position": "F#3",
        "display_name": "Hi-Hat (Closed)"
    },
    {
        "drum_type": "hi-hat",
        "onset_time_seconds": 9.9,
        "midi_pitch": 42,
        "note_head_type": "x",
        "staff_position": "F#3",
        "display_name": "Hi-Hat (Closed)"
    },
    {
        "drum_type": "snare",
        "onset_time_seconds": 10.0,
        "midi_pitch": 38,
        "note_head_type": "normal",
        "staff_position": "C3",
        "display_name": "Snare Drum"
    },
    {
        "drum_type": "snare",
        "onset_time_seconds": 10.1,
        "midi_pitch": 38,
        "note_head_type": "normal",
        "staff_position": "C3",
        "display_name": "Snare Drum"
    },
    {
        "drum_type": "snare",
        "onset_time_seconds": 10.2,
        "midi_pitch": 38,
        "note_head_type": "normal",
        "staff_position": "C3",
        "display_name": "Snare Drum"
    },
    {
        "drum_type": "snare",
        "onset_time_seconds": 10.3,
        "midi_pitch": 38,
        "note_head_type": "normal",
        "staff_position": "C3",
        "display_name": "Snare Drum"
    },
    {
        "drum_type": "hi-hat",
        "onset_time_seconds": 10.6,
        "midi_pitch": 42,
        "note_head_type": "x",
        "staff_position": "F#3",
        "display_name": "Hi-Hat (Closed)"
    },
    {
        "drum_type": "hi-hat",
        "onset_time_seconds": 10.7,
        "midi_pitch": 42,
        "note_head_type": "x",
        "staff_position": "F#3",
        "display_name": "Hi-Hat (Closed)"
    },
    {
        "drum_type": "hi-hat",
        "onset_time_seconds": 10.8,
        "midi_pitch": 42,
        "note_head_type": "x",
        "staff_position": "F#3",
        "display_name": "Hi-Hat (Closed)"
    },
    {
        "drum_type": "hi-hat",
        "onset_time_seconds": 10.9,
        "midi_pitch": 42,
        "note_head_type": "x",
        "staff_position": "F#3",
        "display_name": "Hi-Hat (Closed)"
    },
    {
        "drum_type": "snare",
        "onset_time_seconds": 10.9,
        "midi_pitch": 38,
        "note_head_type": "normal",
        "staff_position": "C3",
        "display_name": "Snare Drum"
    },
    {
        "drum_type": "hi-hat",
        "onset_time_seconds": 11.1,
        "midi_pitch": 42,
        "note_head_type": "x",
        "staff_position": "F#3",
        "display_name": "Hi-Hat (Closed)"
    },
    {
        "drum_type": "hi-hat",
        "onset_time_seconds": 11.3,
        "midi_pitch": 42,
        "note_head_type": "x",
        "staff_position": "F#3",
        "display_name": "Hi-Hat (Closed)"
    },
    {
        "drum_type": "hi-hat",
        "onset_time_seconds": 11.4,
        "midi_pitch": 42,
        "note_head_type": "x",
        "staff_position": "F#3",
        "display_name": "Hi-Hat (Closed)"
    },
    {
        "drum_type": "hi-hat",
        "onset_time_seconds": 11.5,
        "midi_pitch": 42,
        "note_head_type": "x",
        "staff_position": "F#3",
        "display_name": "Hi-Hat (Closed)"
    },
    {
        "drum_type": "hi-hat",
        "onset_time_seconds": 11.6,
        "midi_pitch": 42,
        "note_head_type": "x",
        "staff_position": "F#3",
        "display_name": "Hi-Hat (Closed)"
    },
    {
        "drum_type": "hi-hat",
        "onset_time_seconds": 11.7,
        "midi_pitch": 42,
        "note_head_type": "x",
        "staff_position": "F#3",
        "display_name": "Hi-Hat (Closed)"
    },
    {
        "drum_type": "hi-hat",
        "onset_time_seconds": 11.8,
        "midi_pitch": 42,
        "note_head_type": "x",
        "staff_position": "F#3",
        "display_name": "Hi-Hat (Closed)"
    },
    {
        "drum_type": "snare",
        "onset_time_seconds": 11.9,
        "midi_pitch": 38,
        "note_head_type": "normal",
        "staff_position": "C3",
        "display_name": "Snare Drum"
    },
    {
        "drum_type": "hi-hat",
        "onset_time_seconds": 12.1,
        "midi_pitch": 42,
        "note_head_type": "x",
        "staff_position": "F#3",
        "display_name": "Hi-Hat (Closed)"
    },
    {
        "drum_type": "hi-hat",
        "onset_time_seconds": 12.2,
        "midi_pitch": 42,
        "note_head_type": "x",
        "staff_position": "F#3",
        "display_name": "Hi-Hat (Closed)"
    },
    {
        "drum_type": "hi-hat",
        "onset_time_seconds": 12.3,
        "midi_pitch": 42,
        "note_head_type": "x",
        "staff_position": "F#3",
        "display_name": "Hi-Hat (Closed)"
    },
    {
        "drum_type": "hi-hat",
        "onset_time_seconds": 12.4,
        "midi_pitch": 42,
        "note_head_type": "x",
        "staff_position": "F#3",
        "display_name": "Hi-Hat (Closed)"
    },
    {
        "drum_type": "hi-hat",
        "onset_time_seconds": 12.5,
        "midi_pitch": 42,
        "note_head_type": "x",
        "staff_position": "F#3",
        "display_name": "Hi-Hat (Closed)"
    },
    {
        "drum_type": "hi-hat",
        "onset_time_seconds": 12.9,
        "midi_pitch": 42,
        "note_head_type": "x",
        "staff_position": "F#3",
        "display_name": "Hi-Hat (Closed)"
    },
    {
        "drum_type": "hi-hat",
        "onset_time_seconds": 13.0,
        "midi_pitch": 42,
        "note_head_type": "x",
        "staff_position": "F#3",
        "display_name": "Hi-Hat (Closed)"
    },
    {
        "drum_type": "snare",
        "onset_time_seconds": 13.1,
        "midi_pitch": 38,
        "note_head_type": "normal",
        "staff_position": "C3",
        "display_name": "Snare Drum"
    },
    {
        "drum_type": "snare",
        "onset_time_seconds": 13.2,
        "midi_pitch": 38,
        "note_head_type": "normal",
        "staff_position": "C3",
        "display_name": "Snare Drum"
    },
    {
        "drum_type": "hi-hat",
        "onset_time_seconds": 13.3,
        "midi_pitch": 42,
        "note_head_type": "x",
        "staff_position": "F#3",
        "display_name": "Hi-Hat (Closed)"
    },
    {
        "drum_type": "hi-hat",
        "onset_time_seconds": 13.4,
        "midi_pitch": 42,
        "note_head_type": "x",
        "staff_position": "F#3",
        "display_name": "Hi-Hat (Closed)"
    },
    {
        "drum_type": "hi-hat",
        "onset_time_seconds": 13.5,
        "midi_pitch": 42,
        "note_head_type": "x",
        "staff_position": "F#3",
        "display_name": "Hi-Hat (Closed)"
    },
    {
        "drum_type": "snare",
        "onset_time_seconds": 13.6,
        "midi_pitch": 38,
        "note_head_type": "normal",
        "staff_position": "C3",
        "display_name": "Snare Drum"
    },
    {
        "drum_type": "snare",
        "onset_time_seconds": 13.7,
        "midi_pitch": 38,
        "note_head_type": "normal",
        "staff_position": "C3",
        "display_name": "Snare Drum"
    },
    {
        "drum_type": "hi-hat",
        "onset_time_seconds": 14.1,
        "midi_pitch": 42,
        "note_head_type": "x",
        "staff_position": "F#3",
        "display_name": "Hi-Hat (Closed)"
    },
    {
        "drum_type": "hi-hat",
        "onset_time_seconds": 14.2,
        "midi_pitch": 42,
        "note_head_type": "x",
        "staff_position": "F#3",
        "display_name": "Hi-Hat (Closed)"
    },
    {
        "drum_type": "hi-hat",
        "onset_time_seconds": 14.3,
        "midi_pitch": 42,
        "note_head_type": "x",
        "staff_position": "F#3",
        "display_name": "Hi-Hat (Closed)"
    },
    {
        "drum_type": "hi-hat",
        "onset_time_seconds": 14.4,
        "midi_pitch": 42,
        "note_head_type": "x",
        "staff_position": "F#3",
        "display_name": "Hi-Hat (Closed)"
    },
    {
        "drum_type": "hi-hat",
        "onset_time_seconds": 14.5,
        "midi_pitch": 42,
        "note_head_type": "x",
        "staff_position": "F#3",
        "display_name": "Hi-Hat (Closed)"
    },
    {
        "drum_type": "hi-hat",
        "onset_time_seconds": 14.6,
        "midi_pitch": 42,
        "note_head_type": "x",
        "staff_position": "F#3",
        "display_name": "Hi-Hat (Closed)"
    },
    {
        "drum_type": "hi-hat",
        "onset_time_seconds": 14.7,
        "midi_pitch": 42,
        "note_head_type": "x",
        "staff_position": "F#3",
        "display_name": "Hi-Hat (Closed)"
    },
    {
        "drum_type": "hi-hat",
        "onset_time_seconds": 14.9,
        "midi_pitch": 42,
        "note_head_type": "x",
        "staff_position": "F#3",
        "display_name": "Hi-Hat (Closed)"
    },
    {
        "drum_type": "snare",
        "onset_time_seconds": 15.0,
        "midi_pitch": 38,
        "note_head_type": "normal",
        "staff_position": "C3",
        "display_name": "Snare Drum"
    },
    {
        "drum_type": "hi-hat",
        "onset_time_seconds": 15.1,
        "midi_pitch": 42,
        "note_head_type": "x",
        "staff_position": "F#3",
        "display_name": "Hi-Hat (Closed)"
    },
    {
        "drum_type": "hi-hat",
        "onset_time_seconds": 15.2,
        "midi_pitch": 42,
        "note_head_type": "x",
        "staff_position": "F#3",
        "display_name": "Hi-Hat (Closed)"
    },
    {
        "drum_type": "hi-hat",
        "onset_time_seconds": 15.3,
        "midi_pitch": 42,
        "note_head_type": "x",
        "staff_position": "F#3",
        "display_name": "Hi-Hat (Closed)"
    },
    {
        "drum_type": "hi-hat",
        "onset_time_seconds": 15.4,
        "midi_pitch": 42,
        "note_head_type": "x",
        "staff_position": "F#3",
        "display_name": "Hi-Hat (Closed)"
    },
    {
        "drum_type": "hi-hat",
        "onset_time_seconds": 15.6,
        "midi_pitch": 42,
        "note_head_type": "x",
        "staff_position": "F#3",
        "display_name": "Hi-Hat (Closed)"
    },
    {
        "drum_type": "hi-hat",
        "onset_time_seconds": 15.8,
        "midi_pitch": 42,
        "note_head_type": "x",
        "staff_position": "F#3",
        "display_name": "Hi-Hat (Closed)"
    },
    {
        "drum_type": "hi-hat",
        "onset_time_seconds": 15.9,
        "midi_pitch": 42,
        "note_head_type": "x",
        "staff_position": "F#3",
        "display_name": "Hi-Hat (Closed)"
    },
    {
        "drum_type": "hi-hat",
        "onset_time_seconds": 16.0,
        "midi_pitch": 42,
        "note_head_type": "x",
        "staff_position": "F#3",
        "display_name": "Hi-Hat (Closed)"
    },
    {
        "drum_type": "hi-hat",
        "onset_time_seconds": 16.1,
        "midi_pitch": 42,
        "note_head_type": "x",
        "staff_position": "F#3",
        "display_name": "Hi-Hat (Closed)"
    },
    {
        "drum_type": "hi-hat",
        "onset_time_seconds": 16.2,
        "midi_pitch": 42,
        "note_head_type": "x",
        "staff_position": "F#3",
        "display_name": "Hi-Hat (Closed)"
    },
    {
        "drum_type": "hi-hat",
        "onset_time_seconds": 16.3,
        "midi_pitch": 42,
        "note_head_type": "x",
        "staff_position": "F#3",
        "display_name": "Hi-Hat (Closed)"
    },
    {
        "drum_type": "hi-hat",
        "onset_time_seconds": 16.4,
        "midi_pitch": 42,
        "note_head_type": "x",
        "staff_position": "F#3",
        "display_name": "Hi-Hat (Closed)"
    },
    {
        "drum_type": "kick",
        "onset_time_seconds": 16.5,
        "midi_pitch": 36,
        "note_head_type": "normal",
        "staff_position": "F2",
        "display_name": "Bass Drum"
    },
    {
        "drum_type": "hi-hat",
        "onset_time_seconds": 16.7,
        "midi_pitch": 42,
        "note_head_type": "x",
        "staff_position": "F#3",
        "display_name": "Hi-Hat (Closed)"
    },
    {
        "drum_type": "hi-hat",
        "onset_time_seconds": 16.8,
        "midi_pitch": 42,
        "note_head_type": "x",
        "staff_position": "F#3",
        "display_name": "Hi-Hat (Closed)"
    },
    {
        "drum_type": "hi-hat",
        "onset_time_seconds": 17.0,
        "midi_pitch": 42,
        "note_head_type": "x",
        "staff_position": "F#3",
        "display_name": "Hi-Hat (Closed)"
    },
    {
        "drum_type": "hi-hat",
        "onset_time_seconds": 17.1,
        "midi_pitch": 42,
        "note_head_type": "x",
        "staff_position": "F#3",
        "display_name": "Hi-Hat (Closed)"
    },
    {
        "drum_type": "hi-hat",
        "onset_time_seconds": 17.2,
        "midi_pitch": 42,
        "note_head_type": "x",
        "staff_position": "F#3",
        "display_name": "Hi-Hat (Closed)"
    },
    {
        "drum_type": "hi-hat",
        "onset_time_seconds": 17.3,
        "midi_pitch": 42,
        "note_head_type": "x",
        "staff_position": "F#3",
        "display_name": "Hi-Hat (Closed)"
    },
    {
        "drum_type": "snare",
        "onset_time_seconds": 17.4,
        "midi_pitch": 38,
        "note_head_type": "normal",
        "staff_position": "C3",
        "display_name": "Snare Drum"
    },
    {
        "drum_type": "snare",
        "onset_time_seconds": 17.5,
        "midi_pitch": 38,
        "note_head_type": "normal",
        "staff_position": "C3",
        "display_name": "Snare Drum"
    },
    {
        "drum_type": "snare",
        "onset_time_seconds": 17.6,
        "midi_pitch": 38,
        "note_head_type": "normal",
        "staff_position": "C3",
        "display_name": "Snare Drum"
    },
    {
        "drum_type": "hi-hat",
        "onset_time_seconds": 17.9,
        "midi_pitch": 42,
        "note_head_type": "x",
        "staff_position": "F#3",
        "display_name": "Hi-Hat (Closed)"
    },
    {
        "drum_type": "hi-hat",
        "onset_time_seconds": 18.0,
        "midi_pitch": 42,
        "note_head_type": "x",
        "staff_position": "F#3",
        "display_name": "Hi-Hat (Closed)"
    },
    {
        "drum_type": "hi-hat",
        "onset_time_seconds": 18.1,
        "midi_pitch": 42,
        "note_head_type": "x",
        "staff_position": "F#3",
        "display_name": "Hi-Hat (Closed)"
    },
    {
        "drum_type": "hi-hat",
        "onset_time_seconds": 18.2,
        "midi_pitch": 42,
        "note_head_type": "x",
        "staff_position": "F#3",
        "display_name": "Hi-Hat (Closed)"
    },
    {
        "drum_type": "hi-hat",
        "onset_time_seconds": 18.3,
        "midi_pitch": 42,
        "note_head_type": "x",
        "staff_position": "F#3",
        "display_name": "Hi-Hat (Closed)"
    },
    {
        "drum_type": "hi-hat",
        "onset_time_seconds": 18.4,
        "midi_pitch": 42,
        "note_head_type": "x",
        "staff_position": "F#3",
        "display_name": "Hi-Hat (Closed)"
    },
    {
        "drum_type": "hi-hat",
        "onset_time_seconds": 18.7,
        "midi_pitch": 42,
        "note_head_type": "x",
        "staff_position": "F#3",
        "display_name": "Hi-Hat (Closed)"
    },
    {
        "drum_type": "hi-hat",
        "onset_time_seconds": 18.8,
        "midi_pitch": 42,
        "note_head_type": "x",
        "staff_position": "F#3",
        "display_name": "Hi-Hat (Closed)"
    },
    {
        "drum_type": "hi-hat",
        "onset_time_seconds": 18.9,
        "midi_pitch": 42,
        "note_head_type": "x",
        "staff_position": "F#3",
        "display_name": "Hi-Hat (Closed)"
    },
    {
        "drum_type": "hi-hat",
        "onset_time_seconds": 19.0,
        "midi_pitch": 42,
        "note_head_type": "x",
        "staff_position": "F#3",
        "display_name": "Hi-Hat (Closed)"
    },
    {
        "drum_type": "hi-hat",
        "onset_time_seconds": 19.1,
        "midi_pitch": 42,
        "note_head_type": "x",
        "staff_position": "F#3",
        "display_name": "Hi-Hat (Closed)"
    },
    {
        "drum_type": "hi-hat",
        "onset_time_seconds": 19.3,
        "midi_pitch": 42,
        "note_head_type": "x",
        "staff_position": "F#3",
        "display_name": "Hi-Hat (Closed)"
    },
    {
        "drum_type": "snare",
        "onset_time_seconds": 19.4,
        "midi_pitch": 38,
        "note_head_type": "normal",
        "staff_position": "C3",
        "display_name": "Snare Drum"
    },
    {
        "drum_type": "hi-hat",
        "onset_time_seconds": 19.7,
        "midi_pitch": 42,
        "note_head_type": "x",
        "staff_position": "F#3",
        "display_name": "Hi-Hat (Closed)"
    },
    {
        "drum_type": "snare",
        "onset_time_seconds": 19.7,
        "midi_pitch": 38,
        "note_head_type": "normal",
        "staff_position": "C3",
        "display_name": "Snare Drum"
    },
    {
        "drum_type": "hi-hat",
        "onset_time_seconds": 19.8,
        "midi_pitch": 42,
        "note_head_type": "x",
        "staff_position": "F#3",
        "display_name": "Hi-Hat (Closed)"
    },
    {
        "drum_type": "hi-hat",
        "onset_time_seconds": 19.9,
        "midi_pitch": 42,
        "note_head_type": "x",
        "staff_position": "F#3",
        "display_name": "Hi-Hat (Closed)"
    },
    {
        "drum_type": "hi-hat",
        "onset_time_seconds": 20.0,
        "midi_pitch": 42,
        "note_head_type": "x",
        "staff_position": "F#3",
        "display_name": "Hi-Hat (Closed)"
    },
    {
        "drum_type": "hi-hat",
        "onset_time_seconds": 20.3,
        "midi_pitch": 42,
        "note_head_type": "x",
        "staff_position": "F#3",
        "display_name": "Hi-Hat (Closed)"
    },
    {
        "drum_type": "hi-hat",
        "onset_time_seconds": 20.4,
        "midi_pitch": 42,
        "note_head_type": "x",
        "staff_position": "F#3",
        "display_name": "Hi-Hat (Closed)"
    },
    {
        "drum_type": "hi-hat",
        "onset_time_seconds": 20.5,
        "midi_pitch": 42,
        "note_head_type": "x",
        "staff_position": "F#3",
        "display_name": "Hi-Hat (Closed)"
    },
    {
        "drum_type": "hi-hat",
        "onset_time_seconds": 20.6,
        "midi_pitch": 42,
        "note_head_type": "x",
        "staff_position": "F#3",
        "display_name": "Hi-Hat (Closed)"
    },
    {
        "drum_type": "snare",
        "onset_time_seconds": 20.6,
        "midi_pitch": 38,
        "note_head_type": "normal",
        "staff_position": "C3",
        "display_name": "Snare Drum"
    },
    {
        "drum_type": "hi-hat",
        "onset_time_seconds": 20.7,
        "midi_pitch": 42,
        "note_head_type": "x",
        "staff_position": "F#3",
        "display_name": "Hi-Hat (Closed)"
    },
    {
        "drum_type": "hi-hat",
        "onset_time_seconds": 20.8,
        "midi_pitch": 42,
        "note_head_type": "x",
        "staff_position": "F#3",
        "display_name": "Hi-Hat (Closed)"
    },
    {
        "drum_type": "snare",
        "onset_time_seconds": 20.9,
        "midi_pitch": 38,
        "note_head_type": "normal",
        "staff_position": "C3",
        "display_name": "Snare Drum"
    },
    {
        "drum_type": "hi-hat",
        "onset_time_seconds": 21.1,
        "midi_pitch": 42,
        "note_head_type": "x",
        "staff_position": "F#3",
        "display_name": "Hi-Hat (Closed)"
    },
    {
        "drum_type": "hi-hat",
        "onset_time_seconds": 21.5,
        "midi_pitch": 42,
        "note_head_type": "x",
        "staff_position": "F#3",
        "display_name": "Hi-Hat (Closed)"
    },
    {
        "drum_type": "hi-hat",
        "onset_time_seconds": 21.6,
        "midi_pitch": 42,
        "note_head_type": "x",
        "staff_position": "F#3",
        "display_name": "Hi-Hat (Closed)"
    },
    {
        "drum_type": "hi-hat",
        "onset_time_seconds": 21.7,
        "midi_pitch": 42,
        "note_head_type": "x",
        "staff_position": "F#3",
        "display_name": "Hi-Hat (Closed)"
    },
    {
        "drum_type": "hi-hat",
        "onset_time_seconds": 21.8,
        "midi_pitch": 42,
        "note_head_type": "x",
        "staff_position": "F#3",
        "display_name": "Hi-Hat (Closed)"
    },
    {
        "drum_type": "hi-hat",
        "onset_time_seconds": 21.9,
        "midi_pitch": 42,
        "note_head_type": "x",
        "staff_position": "F#3",
        "display_name": "Hi-Hat (Closed)"
    },
    {
        "drum_type": "hi-hat",
        "onset_time_seconds": 22.0,
        "midi_pitch": 42,
        "note_head_type": "x",
        "staff_position": "F#3",
        "display_name": "Hi-Hat (Closed)"
    },
    {
        "drum_type": "hi-hat",
        "onset_time_seconds": 22.2,
        "midi_pitch": 42,
        "note_head_type": "x",
        "staff_position": "F#3",
        "display_name": "Hi-Hat (Closed)"
    },
    {
        "drum_type": "snare",
        "onset_time_seconds": 22.4,
        "midi_pitch": 38,
        "note_head_type": "normal",
        "staff_position": "C3",
        "display_name": "Snare Drum"
    },
    {
        "drum_type": "hi-hat",
        "onset_time_seconds": 22.5,
        "midi_pitch": 42,
        "note_head_type": "x",
        "staff_position": "F#3",
        "display_name": "Hi-Hat (Closed)"
    },
    {
        "drum_type": "hi-hat",
        "onset_time_seconds": 22.6,
        "midi_pitch": 42,
        "note_head_type": "x",
        "staff_position": "F#3",
        "display_name": "Hi-Hat (Closed)"
    },
    {
        "drum_type": "hi-hat",
        "onset_time_seconds": 22.7,
        "midi_pitch": 42,
        "note_head_type": "x",
        "staff_position": "F#3",
        "display_name": "Hi-Hat (Closed)"
    },
    {
        "drum_type": "hi-hat",
        "onset_time_seconds": 22.8,
        "midi_pitch": 42,
        "note_head_type": "x",
        "staff_position": "F#3",
        "display_name": "Hi-Hat (Closed)"
    },
    {
        "drum_type": "hi-hat",
        "onset_time_seconds": 22.9,
        "midi_pitch": 42,
        "note_head_type": "x",
        "staff_position": "F#3",
        "display_name": "Hi-Hat (Closed)"
    },
    {
        "drum_type": "snare",
        "onset_time_seconds": 23.0,
        "midi_pitch": 38,
        "note_head_type": "normal",
        "staff_position": "C3",
        "display_name": "Snare Drum"
    },
    {
        "drum_type": "snare",
        "onset_time_seconds": 23.3,
        "midi_pitch": 38,
        "note_head_type": "normal",
        "staff_position": "C3",
        "display_name": "Snare Drum"
    },
    {
        "drum_type": "snare",
        "onset_time_seconds": 23.4,
        "midi_pitch": 38,
        "note_head_type": "normal",
        "staff_position": "C3",
        "display_name": "Snare Drum"
    },
    {
        "drum_type": "hi-hat",
        "onset_time_seconds": 23.5,
        "midi_pitch": 42,
        "note_head_type": "x",
        "staff_position": "F#3",
        "display_name": "Hi-Hat (Closed)"
    },
    {
        "drum_type": "hi-hat",
        "onset_time_seconds": 23.6,
        "midi_pitch": 42,
        "note_head_type": "x",
        "staff_position": "F#3",
        "display_name": "Hi-Hat (Closed)"
    },
    {
        "drum_type": "hi-hat",
        "onset_time_seconds": 23.7,
        "midi_pitch": 42,
        "note_head_type": "x",
        "staff_position": "F#3",
        "display_name": "Hi-Hat (Closed)"
    },
    {
        "drum_type": "hi-hat",
        "onset_time_seconds": 23.9,
        "midi_pitch": 42,
        "note_head_type": "x",
        "staff_position": "F#3",
        "display_name": "Hi-Hat (Closed)"
    },
    {
        "drum_type": "hi-hat",
        "onset_time_seconds": 24.2,
        "midi_pitch": 42,
        "note_head_type": "x",
        "staff_position": "F#3",
        "display_name": "Hi-Hat (Closed)"
    },
    {
        "drum_type": "snare",
        "onset_time_seconds": 24.3,
        "midi_pitch": 38,
        "note_head_type": "normal",
        "staff_position": "C3",
        "display_name": "Snare Drum"
    },
    {
        "drum_type": "hi-hat",
        "onset_time_seconds": 24.4,
        "midi_pitch": 42,
        "note_head_type": "x",
        "staff_position": "F#3",
        "display_name": "Hi-Hat (Closed)"
    },
    {
        "drum_type": "hi-hat",
        "onset_time_seconds": 24.5,
        "midi_pitch": 42,
        "note_head_type": "x",
        "staff_position": "F#3",
        "display_name": "Hi-Hat (Closed)"
    },
    {
        "drum_type": "hi-hat",
        "onset_time_seconds": 24.6,
        "midi_pitch": 42,
        "note_head_type": "x",
        "staff_position": "F#3",
        "display_name": "Hi-Hat (Closed)"
    },
    {
        "drum_type": "hi-hat",
        "onset_time_seconds": 24.7,
        "midi_pitch": 42,
        "note_head_type": "x",
        "staff_position": "F#3",
        "display_name": "Hi-Hat (Closed)"
    },
    {
        "drum_type": "snare",
        "onset_time_seconds": 24.8,
        "midi_pitch": 38,
        "note_head_type": "normal",
        "staff_position": "C3",
        "display_name": "Snare Drum"
    },
    {
        "drum_type": "snare",
        "onset_time_seconds": 25.1,
        "midi_pitch": 38,
        "note_head_type": "normal",
        "staff_position": "C3",
        "display_name": "Snare Drum"
    },
    {
        "drum_type": "snare",
        "onset_time_seconds": 25.2,
        "midi_pitch": 38,
        "note_head_type": "normal",
        "staff_position": "C3",
        "display_name": "Snare Drum"
    },
    {
        "drum_type": "hi-hat",
        "onset_time_seconds": 25.4,
        "midi_pitch": 42,
        "note_head_type": "x",
        "staff_position": "F#3",
        "display_name": "Hi-Hat (Closed)"
    },
    {
        "drum_type": "hi-hat",
        "onset_time_seconds": 25.5,
        "midi_pitch": 42,
        "note_head_type": "x",
        "staff_position": "F#3",
        "display_name": "Hi-Hat (Closed)"
    },
    {
        "drum_type": "hi-hat",
        "onset_time_seconds": 25.6,
        "midi_pitch": 42,
        "note_head_type": "x",
        "staff_position": "F#3",
        "display_name": "Hi-Hat (Closed)"
    },
    {
        "drum_type": "hi-hat",
        "onset_time_seconds": 25.9,
        "midi_pitch": 42,
        "note_head_type": "x",
        "staff_position": "F#3",
        "display_name": "Hi-Hat (Closed)"
    },
    {
        "drum_type": "snare",
        "onset_time_seconds": 26.1,
        "midi_pitch": 38,
        "note_head_type": "normal",
        "staff_position": "C3",
        "display_name": "Snare Drum"
    },
    {
        "drum_type": "hi-hat",
        "onset_time_seconds": 26.2,
        "midi_pitch": 42,
        "note_head_type": "x",
        "staff_position": "F#3",
        "display_name": "Hi-Hat (Closed)"
    },
    {
        "drum_type": "hi-hat",
        "onset_time_seconds": 26.3,
        "midi_pitch": 42,
        "note_head_type": "x",
        "staff_position": "F#3",
        "display_name": "Hi-Hat (Closed)"
    },
    {
        "drum_type": "hi-hat",
        "onset_time_seconds": 26.4,
        "midi_pitch": 42,
        "note_head_type": "x",
        "staff_position": "F#3",
        "display_name": "Hi-Hat (Closed)"
    },
    {
        "drum_type": "hi-hat",
        "onset_time_seconds": 26.5,
        "midi_pitch": 42,
        "note_head_type": "x",
        "staff_position": "F#3",
        "display_name": "Hi-Hat (Closed)"
    },
    {
        "drum_type": "hi-hat",
        "onset_time_seconds": 26.6,
        "midi_pitch": 42,
        "note_head_type": "x",
        "staff_position": "F#3",
        "display_name": "Hi-Hat (Closed)"
    },
    {
        "drum_type": "hi-hat",
        "onset_time_seconds": 26.7,
        "midi_pitch": 42,
        "note_head_type": "x",
        "staff_position": "F#3",
        "display_name": "Hi-Hat (Closed)"
    },
    {
        "drum_type": "snare",
        "onset_time_seconds": 26.8,
        "midi_pitch": 38,
        "note_head_type": "normal",
        "staff_position": "C3",
        "display_name": "Snare Drum"
    },
    {
        "drum_type": "hi-hat",
        "onset_time_seconds": 27.1,
        "midi_pitch": 42,
        "note_head_type": "x",
        "staff_position": "F#3",
        "display_name": "Hi-Hat (Closed)"
    },
    {
        "drum_type": "hi-hat",
        "onset_time_seconds": 27.2,
        "midi_pitch": 42,
        "note_head_type": "x",
        "staff_position": "F#3",
        "display_name": "Hi-Hat (Closed)"
    },
    {
        "drum_type": "hi-hat",
        "onset_time_seconds": 27.3,
        "midi_pitch": 42,
        "note_head_type": "x",
        "staff_position": "F#3",
        "display_name": "Hi-Hat (Closed)"
    },
    {
        "drum_type": "snare",
        "onset_time_seconds": 27.5,
        "midi_pitch": 38,
        "note_head_type": "normal",
        "staff_position": "C3",
        "display_name": "Snare Drum"
    },
    {
        "drum_type": "hi-hat",
        "onset_time_seconds": 27.7,
        "midi_pitch": 42,
        "note_head_type": "x",
        "staff_position": "F#3",
        "display_name": "Hi-Hat (Closed)"
    },
    {
        "drum_type": "hi-hat",
        "onset_time_seconds": 27.8,
        "midi_pitch": 42,
        "note_head_type": "x",
        "staff_position": "F#3",
        "display_name": "Hi-Hat (Closed)"
    },
    {
        "drum_type": "snare",
        "onset_time_seconds": 27.9,
        "midi_pitch": 38,
        "note_head_type": "normal",
        "staff_position": "C3",
        "display_name": "Snare Drum"
    },
    {
        "drum_type": "hi-hat",
        "onset_time_seconds": 28.1,
        "midi_pitch": 42,
        "note_head_type": "x",
        "staff_position": "F#3",
        "display_name": "Hi-Hat (Closed)"
    },
    {
        "drum_type": "hi-hat",
        "onset_time_seconds": 28.2,
        "midi_pitch": 42,
        "note_head_type": "x",
        "staff_position": "F#3",
        "display_name": "Hi-Hat (Closed)"
    },
    {
        "drum_type": "snare",
        "onset_time_seconds": 28.3,
        "midi_pitch": 38,
        "note_head_type": "normal",
        "staff_position": "C3",
        "display_name": "Snare Drum"
    },
    {
        "drum_type": "snare",
        "onset_time_seconds": 28.5,
        "midi_pitch": 38,
        "note_head_type": "normal",
        "staff_position": "C3",
        "display_name": "Snare Drum"
    },
    {
        "drum_type": "snare",
        "onset_time_seconds": 28.7,
        "midi_pitch": 38,
        "note_head_type": "normal",
        "staff_position": "C3",
        "display_name": "Snare Drum"
    },
    {
        "drum_type": "snare",
        "onset_time_seconds": 28.8,
        "midi_pitch": 38,
        "note_head_type": "normal",
        "staff_position": "C3",
        "display_name": "Snare Drum"
    },
    {
        "drum_type": "hi-hat",
        "onset_time_seconds": 29.0,
        "midi_pitch": 42,
        "note_head_type": "x",
        "staff_position": "F#3",
        "display_name": "Hi-Hat (Closed)"
    },
    {
        "drum_type": "hi-hat",
        "onset_time_seconds": 29.1,
        "midi_pitch": 42,
        "note_head_type": "x",
        "staff_position": "F#3",
        "display_name": "Hi-Hat (Closed)"
    },
    {
        "drum_type": "hi-hat",
        "onset_time_seconds": 29.2,
        "midi_pitch": 42,
        "note_head_type": "x",
        "staff_position": "F#3",
        "display_name": "Hi-Hat (Closed)"
    },
    {
        "drum_type": "hi-hat",
        "onset_time_seconds": 29.3,
        "midi_pitch": 42,
        "note_head_type": "x",
        "staff_position": "F#3",
        "display_name": "Hi-Hat (Closed)"
    },
    {
        "drum_type": "hi-hat",
        "onset_time_seconds": 29.4,
        "midi_pitch": 42,
        "note_head_type": "x",
        "staff_position": "F#3",
        "display_name": "Hi-Hat (Closed)"
    },
    {
        "drum_type": "hi-hat",
        "onset_time_seconds": 29.5,
        "midi_pitch": 42,
        "note_head_type": "x",
        "staff_position": "F#3",
        "display_name": "Hi-Hat (Closed)"
    },
    {
        "drum_type": "hi-hat",
        "onset_time_seconds": 29.6,
        "midi_pitch": 42,
        "note_head_type": "x",
        "staff_position": "F#3",
        "display_name": "Hi-Hat (Closed)"
    },
    {
        "drum_type": "hi-hat",
        "onset_time_seconds": 29.7,
        "midi_pitch": 42,
        "note_head_type": "x",
        "staff_position": "F#3",
        "display_name": "Hi-Hat (Closed)"
    },
    {
        "drum_type": "snare",
        "onset_time_seconds": 29.8,
        "midi_pitch": 38,
        "note_head_type": "normal",
        "staff_position": "C3",
        "display_name": "Snare Drum"
    },
    {
        "drum_type": "hi-hat",
        "onset_time_seconds": 30.0,
        "midi_pitch": 42,
        "note_head_type": "x",
        "staff_position": "F#3",
        "display_name": "Hi-Hat (Closed)"
    },
    {
        "drum_type": "hi-hat",
        "onset_time_seconds": 30.1,
        "midi_pitch": 42,
        "note_head_type": "x",
        "staff_position": "F#3",
        "display_name": "Hi-Hat (Closed)"
    },
    {
        "drum_type": "hi-hat",
        "onset_time_seconds": 30.2,
        "midi_pitch": 42,
        "note_head_type": "x",
        "staff_position": "F#3",
        "display_name": "Hi-Hat (Closed)"
    },
    {
        "drum_type": "hi-hat",
        "onset_time_seconds": 30.3,
        "midi_pitch": 42,
        "note_head_type": "x",
        "staff_position": "F#3",
        "display_name": "Hi-Hat (Closed)"
    },
    {
        "drum_type": "hi-hat",
        "onset_time_seconds": 30.4,
        "midi_pitch": 42,
        "note_head_type": "x",
        "staff_position": "F#3",
        "display_name": "Hi-Hat (Closed)"
    },
    {
        "drum_type": "snare",
        "onset_time_seconds": 30.5,
        "midi_pitch": 38,
        "note_head_type": "normal",
        "staff_position": "C3",
        "display_name": "Snare Drum"
    },
    {
        "drum_type": "hi-hat",
        "onset_time_seconds": 30.8,
        "midi_pitch": 42,
        "note_head_type": "x",
        "staff_position": "F#3",
        "display_name": "Hi-Hat (Closed)"
    },
    {
        "drum_type": "hi-hat",
        "onset_time_seconds": 30.9,
        "midi_pitch": 42,
        "note_head_type": "x",
        "staff_position": "F#3",
        "display_name": "Hi-Hat (Closed)"
    },
    {
        "drum_type": "hi-hat",
        "onset_time_seconds": 31.0,
        "midi_pitch": 42,
        "note_head_type": "x",
        "staff_position": "F#3",
        "display_name": "Hi-Hat (Closed)"
    },
    {
        "drum_type": "hi-hat",
        "onset_time_seconds": 31.3,
        "midi_pitch": 42,
        "note_head_type": "x",
        "staff_position": "F#3",
        "display_name": "Hi-Hat (Closed)"
    },
    {
        "drum_type": "hi-hat",
        "onset_time_seconds": 31.4,
        "midi_pitch": 42,
        "note_head_type": "x",
        "staff_position": "F#3",
        "display_name": "Hi-Hat (Closed)"
    },
    {
        "drum_type": "hi-hat",
        "onset_time_seconds": 31.5,
        "midi_pitch": 42,
        "note_head_type": "x",
        "staff_position": "F#3",
        "display_name": "Hi-Hat (Closed)"
    },
    {
        "drum_type": "hi-hat",
        "onset_time_seconds": 31.6,
        "midi_pitch": 42,
        "note_head_type": "x",
        "staff_position": "F#3",
        "display_name": "Hi-Hat (Closed)"
    },
    {
        "drum_type": "hi-hat",
        "onset_time_seconds": 31.7,
        "midi_pitch": 42,
        "note_head_type": "x",
        "staff_position": "F#3",
        "display_name": "Hi-Hat (Closed)"
    },
    {
        "drum_type": "hi-hat",
        "onset_time_seconds": 31.8,
        "midi_pitch": 42,
        "note_head_type": "x",
        "staff_position": "F#3",
        "display_name": "Hi-Hat (Closed)"
    },
    {
        "drum_type": "hi-hat",
        "onset_time_seconds": 31.9,
        "midi_pitch": 42,
        "note_head_type": "x",
        "staff_position": "F#3",
        "display_name": "Hi-Hat (Closed)"
    },
    {
        "drum_type": "hi-hat",
        "onset_time_seconds": 32.0,
        "midi_pitch": 42,
        "note_head_type": "x",
        "staff_position": "F#3",
        "display_name": "Hi-Hat (Closed)"
    },
    {
        "drum_type": "hi-hat",
        "onset_time_seconds": 32.1,
        "midi_pitch": 42,
        "note_head_type": "x",
        "staff_position": "F#3",
        "display_name": "Hi-Hat (Closed)"
    },
    {
        "drum_type": "hi-hat",
        "onset_time_seconds": 32.2,
        "midi_pitch": 42,
        "note_head_type": "x",
        "staff_position": "F#3",
        "display_name": "Hi-Hat (Closed)"
    },
    {
        "drum_type": "snare",
        "onset_time_seconds": 32.3,
        "midi_pitch": 38,
        "note_head_type": "normal",
        "staff_position": "C3",
        "display_name": "Snare Drum"
    },
    {
        "drum_type": "hi-hat",
        "onset_time_seconds": 32.6,
        "midi_pitch": 42,
        "note_head_type": "x",
        "staff_position": "F#3",
        "display_name": "Hi-Hat (Closed)"
    },
    {
        "drum_type": "hi-hat",
        "onset_time_seconds": 32.7,
        "midi_pitch": 42,
        "note_head_type": "x",
        "staff_position": "F#3",
        "display_name": "Hi-Hat (Closed)"
    },
    {
        "drum_type": "hi-hat",
        "onset_time_seconds": 32.8,
        "midi_pitch": 42,
        "note_head_type": "x",
        "staff_position": "F#3",
        "display_name": "Hi-Hat (Closed)"
    },
    {
        "drum_type": "hi-hat",
        "onset_time_seconds": 32.9,
        "midi_pitch": 42,
        "note_head_type": "x",
        "staff_position": "F#3",
        "display_name": "Hi-Hat (Closed)"
    },
    {
        "drum_type": "hi-hat",
        "onset_time_seconds": 33.0,
        "midi_pitch": 42,
        "note_head_type": "x",
        "staff_position": "F#3",
        "display_name": "Hi-Hat (Closed)"
    },
    {
        "drum_type": "hi-hat",
        "onset_time_seconds": 33.3,
        "midi_pitch": 42,
        "note_head_type": "x",
        "staff_position": "F#3",
        "display_name": "Hi-Hat (Closed)"
    },
    {
        "drum_type": "snare",
        "onset_time_seconds": 33.4,
        "midi_pitch": 38,
        "note_head_type": "normal",
        "staff_position": "C3",
        "display_name": "Snare Drum"
    },
    {
        "drum_type": "snare",
        "onset_time_seconds": 33.5,
        "midi_pitch": 38,
        "note_head_type": "normal",
        "staff_position": "C3",
        "display_name": "Snare Drum"
    },
    {
        "drum_type": "hi-hat",
        "onset_time_seconds": 33.6,
        "midi_pitch": 42,
        "note_head_type": "x",
        "staff_position": "F#3",
        "display_name": "Hi-Hat (Closed)"
    },
    {
        "drum_type": "hi-hat",
        "onset_time_seconds": 33.7,
        "midi_pitch": 42,
        "note_head_type": "x",
        "staff_position": "F#3",
        "display_name": "Hi-Hat (Closed)"
    },
    {
        "drum_type": "hi-hat",
        "onset_time_seconds": 33.8,
        "midi_pitch": 42,
        "note_head_type": "x",
        "staff_position": "F#3",
        "display_name": "Hi-Hat (Closed)"
    },
    {
        "drum_type": "hi-hat",
        "onset_time_seconds": 33.9,
        "midi_pitch": 42,
        "note_head_type": "x",
        "staff_position": "F#3",
        "display_name": "Hi-Hat (Closed)"
    },
    {
        "drum_type": "snare",
        "onset_time_seconds": 34.0,
        "midi_pitch": 38,
        "note_head_type": "normal",
        "staff_position": "C3",
        "display_name": "Snare Drum"
    },
    {
        "drum_type": "snare",
        "onset_time_seconds": 34.1,
        "midi_pitch": 38,
        "note_head_type": "normal",
        "staff_position": "C3",
        "display_name": "Snare Drum"
    },
    {
        "drum_type": "snare",
        "onset_time_seconds": 34.2,
        "midi_pitch": 38,
        "note_head_type": "normal",
        "staff_position": "C3",
        "display_name": "Snare Drum"
    },
    {
        "drum_type": "hi-hat",
        "onset_time_seconds": 34.5,
        "midi_pitch": 42,
        "note_head_type": "x",
        "staff_position": "F#3",
        "display_name": "Hi-Hat (Closed)"
    },
    {
        "drum_type": "hi-hat",
        "onset_time_seconds": 34.6,
        "midi_pitch": 42,
        "note_head_type": "x",
        "staff_position": "F#3",
        "display_name": "Hi-Hat (Closed)"
    },
    {
        "drum_type": "hi-hat",
        "onset_time_seconds": 34.7,
        "midi_pitch": 42,
        "note_head_type": "x",
        "staff_position": "F#3",
        "display_name": "Hi-Hat (Closed)"
    },
    {
        "drum_type": "hi-hat",
        "onset_time_seconds": 35.1,
        "midi_pitch": 42,
        "note_head_type": "x",
        "staff_position": "F#3",
        "display_name": "Hi-Hat (Closed)"
    },
    {
        "drum_type": "hi-hat",
        "onset_time_seconds": 35.2,
        "midi_pitch": 42,
        "note_head_type": "x",
        "staff_position": "F#3",
        "display_name": "Hi-Hat (Closed)"
    },
    {
        "drum_type": "hi-hat",
        "onset_time_seconds": 35.3,
        "midi_pitch": 42,
        "note_head_type": "x",
        "staff_position": "F#3",
        "display_name": "Hi-Hat (Closed)"
    },
    {
        "drum_type": "hi-hat",
        "onset_time_seconds": 35.4,
        "midi_pitch": 42,
        "note_head_type": "x",
        "staff_position": "F#3",
        "display_name": "Hi-Hat (Closed)"
    },
    {
        "drum_type": "hi-hat",
        "onset_time_seconds": 35.5,
        "midi_pitch": 42,
        "note_head_type": "x",
        "staff_position": "F#3",
        "display_name": "Hi-Hat (Closed)"
    },
    {
        "drum_type": "hi-hat",
        "onset_time_seconds": 35.6,
        "midi_pitch": 42,
        "note_head_type": "x",
        "staff_position": "F#3",
        "display_name": "Hi-Hat (Closed)"
    },
    {
        "drum_type": "snare",
        "onset_time_seconds": 35.7,
        "midi_pitch": 38,
        "note_head_type": "normal",
        "staff_position": "C3",
        "display_name": "Snare Drum"
    },
    {
        "drum_type": "hi-hat",
        "onset_time_seconds": 35.9,
        "midi_pitch": 42,
        "note_head_type": "x",
        "staff_position": "F#3",
        "display_name": "Hi-Hat (Closed)"
    },
    {
        "drum_type": "snare",
        "onset_time_seconds": 36.1,
        "midi_pitch": 38,
        "note_head_type": "normal",
        "staff_position": "C3",
        "display_name": "Snare Drum"
    },
    {
        "drum_type": "hi-hat",
        "onset_time_seconds": 36.3,
        "midi_pitch": 42,
        "note_head_type": "x",
        "staff_position": "F#3",
        "display_name": "Hi-Hat (Closed)"
    },
    {
        "drum_type": "hi-hat",
        "onset_time_seconds": 36.5,
        "midi_pitch": 42,
        "note_head_type": "x",
        "staff_position": "F#3",
        "display_name": "Hi-Hat (Closed)"
    },
    {
        "drum_type": "hi-hat",
        "onset_time_seconds": 36.6,
        "midi_pitch": 42,
        "note_head_type": "x",
        "staff_position": "F#3",
        "display_name": "Hi-Hat (Closed)"
    },
    {
        "drum_type": "hi-hat",
        "onset_time_seconds": 36.7,
        "midi_pitch": 42,
        "note_head_type": "x",
        "staff_position": "F#3",
        "display_name": "Hi-Hat (Closed)"
    },
    {
        "drum_type": "kick",
        "onset_time_seconds": 36.8,
        "midi_pitch": 36,
        "note_head_type": "normal",
        "staff_position": "F2",
        "display_name": "Bass Drum"
    },
    {
        "drum_type": "hi-hat",
        "onset_time_seconds": 36.9,
        "midi_pitch": 42,
        "note_head_type": "x",
        "staff_position": "F#3",
        "display_name": "Hi-Hat (Closed)"
    },
    {
        "drum_type": "snare",
        "onset_time_seconds": 37.2,
        "midi_pitch": 38,
        "note_head_type": "normal",
        "staff_position": "C3",
        "display_name": "Snare Drum"
    },
    {
        "drum_type": "hi-hat",
        "onset_time_seconds": 37.4,
        "midi_pitch": 42,
        "note_head_type": "x",
        "staff_position": "F#3",
        "display_name": "Hi-Hat (Closed)"
    },
    {
        "drum_type": "hi-hat",
        "onset_time_seconds": 37.5,
        "midi_pitch": 42,
        "note_head_type": "x",
        "staff_position": "F#3",
        "display_name": "Hi-Hat (Closed)"
    },
    {
        "drum_type": "hi-hat",
        "onset_time_seconds": 37.6,
        "midi_pitch": 42,
        "note_head_type": "x",
        "staff_position": "F#3",
        "display_name": "Hi-Hat (Closed)"
    },
    {
        "drum_type": "snare",
        "onset_time_seconds": 37.7,
        "midi_pitch": 38,
        "note_head_type": "normal",
        "staff_position": "C3",
        "display_name": "Snare Drum"
    },
    {
        "drum_type": "hi-hat",
        "onset_time_seconds": 37.8,
        "midi_pitch": 42,
        "note_head_type": "x",
        "staff_position": "F#3",
        "display_name": "Hi-Hat (Closed)"
    },
    {
        "drum_type": "snare",
        "onset_time_seconds": 37.9,
        "midi_pitch": 38,
        "note_head_type": "normal",
        "staff_position": "C3",
        "display_name": "Snare Drum"
    },
    {
        "drum_type": "hi-hat",
        "onset_time_seconds": 38.2,
        "midi_pitch": 42,
        "note_head_type": "x",
        "staff_position": "F#3",
        "display_name": "Hi-Hat (Closed)"
    },
    {
        "drum_type": "hi-hat",
        "onset_time_seconds": 38.3,
        "midi_pitch": 42,
        "note_head_type": "x",
        "staff_position": "F#3",
        "display_name": "Hi-Hat (Closed)"
    },
    {
        "drum_type": "hi-hat",
        "onset_time_seconds": 38.4,
        "midi_pitch": 42,
        "note_head_type": "x",
        "staff_position": "F#3",
        "display_name": "Hi-Hat (Closed)"
    },
    {
        "drum_type": "hi-hat",
        "onset_time_seconds": 38.8,
        "midi_pitch": 42,
        "note_head_type": "x",
        "staff_position": "F#3",
        "display_name": "Hi-Hat (Closed)"
    },
    {
        "drum_type": "hi-hat",
        "onset_time_seconds": 38.9,
        "midi_pitch": 42,
        "note_head_type": "x",
        "staff_position": "F#3",
        "display_name": "Hi-Hat (Closed)"
    },
    {
        "drum_type": "hi-hat",
        "onset_time_seconds": 39.0,
        "midi_pitch": 42,
        "note_head_type": "x",
        "staff_position": "F#3",
        "display_name": "Hi-Hat (Closed)"
    },
    {
        "drum_type": "hi-hat",
        "onset_time_seconds": 39.1,
        "midi_pitch": 42,
        "note_head_type": "x",
        "staff_position": "F#3",
        "display_name": "Hi-Hat (Closed)"
    },
    {
        "drum_type": "hi-hat",
        "onset_time_seconds": 39.2,
        "midi_pitch": 42,
        "note_head_type": "x",
        "staff_position": "F#3",
        "display_name": "Hi-Hat (Closed)"
    },
    {
        "drum_type": "hi-hat",
        "onset_time_seconds": 39.3,
        "midi_pitch": 42,
        "note_head_type": "x",
        "staff_position": "F#3",
        "display_name": "Hi-Hat (Closed)"
    },
    {
        "drum_type": "hi-hat",
        "onset_time_seconds": 39.4,
        "midi_pitch": 42,
        "note_head_type": "x",
        "staff_position": "F#3",
        "display_name": "Hi-Hat (Closed)"
    },
    {
        "drum_type": "hi-hat",
        "onset_time_seconds": 39.5,
        "midi_pitch": 42,
        "note_head_type": "x",
        "staff_position": "F#3",
        "display_name": "Hi-Hat (Closed)"
    },
    {
        "drum_type": "hi-hat",
        "onset_time_seconds": 39.6,
        "midi_pitch": 42,
        "note_head_type": "x",
        "staff_position": "F#3",
        "display_name": "Hi-Hat (Closed)"
    },
    {
        "drum_type": "hi-hat",
        "onset_time_seconds": 40.0,
        "midi_pitch": 42,
        "note_head_type": "x",
        "staff_position": "F#3",
        "display_name": "Hi-Hat (Closed)"
    },
    {
        "drum_type": "hi-hat",
        "onset_time_seconds": 40.1,
        "midi_pitch": 42,
        "note_head_type": "x",
        "staff_position": "F#3",
        "display_name": "Hi-Hat (Closed)"
    },
    {
        "drum_type": "hi-hat",
        "onset_time_seconds": 40.2,
        "midi_pitch": 42,
        "note_head_type": "x",
        "staff_position": "F#3",
        "display_name": "Hi-Hat (Closed)"
    },
    {
        "drum_type": "hi-hat",
        "onset_time_seconds": 40.3,
        "midi_pitch": 42,
        "note_head_type": "x",
        "staff_position": "F#3",
        "display_name": "Hi-Hat (Closed)"
    },
    {
        "drum_type": "hi-hat",
        "onset_time_seconds": 40.4,
        "midi_pitch": 42,
        "note_head_type": "x",
        "staff_position": "F#3",
        "display_name": "Hi-Hat (Closed)"
    },
    {
        "drum_type": "kick",
        "onset_time_seconds": 40.5,
        "midi_pitch": 36,
        "note_head_type": "normal",
        "staff_position": "F2",
        "display_name": "Bass Drum"
    },
    {
        "drum_type": "snare",
        "onset_time_seconds": 40.6,
        "midi_pitch": 38,
        "note_head_type": "normal",
        "staff_position": "C3",
        "display_name": "Snare Drum"
    },
    {
        "drum_type": "hi-hat",
        "onset_time_seconds": 40.7,
        "midi_pitch": 42,
        "note_head_type": "x",
        "staff_position": "F#3",
        "display_name": "Hi-Hat (Closed)"
    },
    {
        "drum_type": "snare",
        "onset_time_seconds": 40.8,
        "midi_pitch": 38,
        "note_head_type": "normal",
        "staff_position": "C3",
        "display_name": "Snare Drum"
    },
    {
        "drum_type": "snare",
        "onset_time_seconds": 40.9,
        "midi_pitch": 38,
        "note_head_type": "normal",
        "staff_position": "C3",
        "display_name": "Snare Drum"
    },
    {
        "drum_type": "hi-hat",
        "onset_time_seconds": 41.1,
        "midi_pitch": 42,
        "note_head_type": "x",
        "staff_position": "F#3",
        "display_name": "Hi-Hat (Closed)"
    },
    {
        "drum_type": "hi-hat",
        "onset_time_seconds": 41.2,
        "midi_pitch": 42,
        "note_head_type": "x",
        "staff_position": "F#3",
        "display_name": "Hi-Hat (Closed)"
    },
    {
        "drum_type": "hi-hat",
        "onset_time_seconds": 41.3,
        "midi_pitch": 42,
        "note_head_type": "x",
        "staff_position": "F#3",
        "display_name": "Hi-Hat (Closed)"
    },
    {
        "drum_type": "snare",
        "onset_time_seconds": 41.5,
        "midi_pitch": 38,
        "note_head_type": "normal",
        "staff_position": "C3",
        "display_name": "Snare Drum"
    },
    {
        "drum_type": "snare",
        "onset_time_seconds": 41.6,
        "midi_pitch": 38,
        "note_head_type": "normal",
        "staff_position": "C3",
        "display_name": "Snare Drum"
    },
    {
        "drum_type": "snare",
        "onset_time_seconds": 41.8,
        "midi_pitch": 38,
        "note_head_type": "normal",
        "staff_position": "C3",
        "display_name": "Snare Drum"
    },
    {
        "drum_type": "hi-hat",
        "onset_time_seconds": 41.9,
        "midi_pitch": 42,
        "note_head_type": "x",
        "staff_position": "F#3",
        "display_name": "Hi-Hat (Closed)"
    },
    {
        "drum_type": "hi-hat",
        "onset_time_seconds": 42.0,
        "midi_pitch": 42,
        "note_head_type": "x",
        "staff_position": "F#3",
        "display_name": "Hi-Hat (Closed)"
    },
    {
        "drum_type": "hi-hat",
        "onset_time_seconds": 42.1,
        "midi_pitch": 42,
        "note_head_type": "x",
        "staff_position": "F#3",
        "display_name": "Hi-Hat (Closed)"
    },
    {
        "drum_type": "hi-hat",
        "onset_time_seconds": 42.3,
        "midi_pitch": 42,
        "note_head_type": "x",
        "staff_position": "F#3",
        "display_name": "Hi-Hat (Closed)"
    },
    {
        "drum_type": "kick",
        "onset_time_seconds": 42.4,
        "midi_pitch": 36,
        "note_head_type": "normal",
        "staff_position": "F2",
        "display_name": "Bass Drum"
    },
    {
        "drum_type": "hi-hat",
        "onset_time_seconds": 42.5,
        "midi_pitch": 42,
        "note_head_type": "x",
        "staff_position": "F#3",
        "display_name": "Hi-Hat (Closed)"
    },
    {
        "drum_type": "hi-hat",
        "onset_time_seconds": 42.6,
        "midi_pitch": 42,
        "note_head_type": "x",
        "staff_position": "F#3",
        "display_name": "Hi-Hat (Closed)"
    },
    {
        "drum_type": "hi-hat",
        "onset_time_seconds": 42.7,
        "midi_pitch": 42,
        "note_head_type": "x",
        "staff_position": "F#3",
        "display_name": "Hi-Hat (Closed)"
    },
    {
        "drum_type": "hi-hat",
        "onset_time_seconds": 42.8,
        "midi_pitch": 42,
        "note_head_type": "x",
        "staff_position": "F#3",
        "display_name": "Hi-Hat (Closed)"
    },
    {
        "drum_type": "hi-hat",
        "onset_time_seconds": 42.9,
        "midi_pitch": 42,
        "note_head_type": "x",
        "staff_position": "F#3",
        "display_name": "Hi-Hat (Closed)"
    },
    {
        "drum_type": "hi-hat",
        "onset_time_seconds": 43.0,
        "midi_pitch": 42,
        "note_head_type": "x",
        "staff_position": "F#3",
        "display_name": "Hi-Hat (Closed)"
    },
    {
        "drum_type": "snare",
        "onset_time_seconds": 43.1,
        "midi_pitch": 38,
        "note_head_type": "normal",
        "staff_position": "C3",
        "display_name": "Snare Drum"
    },
    {
        "drum_type": "snare",
        "onset_time_seconds": 43.2,
        "midi_pitch": 38,
        "note_head_type": "normal",
        "staff_position": "C3",
        "display_name": "Snare Drum"
    },
    {
        "drum_type": "snare",
        "onset_time_seconds": 43.3,
        "midi_pitch": 38,
        "note_head_type": "normal",
        "staff_position": "C3",
        "display_name": "Snare Drum"
    },
    {
        "drum_type": "snare",
        "onset_time_seconds": 43.5,
        "midi_pitch": 38,
        "note_head_type": "normal",
        "staff_position": "C3",
        "display_name": "Snare Drum"
    },
    {
        "drum_type": "hi-hat",
        "onset_time_seconds": 43.7,
        "midi_pitch": 42,
        "note_head_type": "x",
        "staff_position": "F#3",
        "display_name": "Hi-Hat (Closed)"
    },
    {
        "drum_type": "hi-hat",
        "onset_time_seconds": 43.8,
        "midi_pitch": 42,
        "note_head_type": "x",
        "staff_position": "F#3",
        "display_name": "Hi-Hat (Closed)"
    },
    {
        "drum_type": "hi-hat",
        "onset_time_seconds": 43.9,
        "midi_pitch": 42,
        "note_head_type": "x",
        "staff_position": "F#3",
        "display_name": "Hi-Hat (Closed)"
    },
    {
        "drum_type": "hi-hat",
        "onset_time_seconds": 44.0,
        "midi_pitch": 42,
        "note_head_type": "x",
        "staff_position": "F#3",
        "display_name": "Hi-Hat (Closed)"
    },
    {
        "drum_type": "hi-hat",
        "onset_time_seconds": 44.2,
        "midi_pitch": 42,
        "note_head_type": "x",
        "staff_position": "F#3",
        "display_name": "Hi-Hat (Closed)"
    },
    {
        "drum_type": "hi-hat",
        "onset_time_seconds": 44.3,
        "midi_pitch": 42,
        "note_head_type": "x",
        "staff_position": "F#3",
        "display_name": "Hi-Hat (Closed)"
    },
    {
        "drum_type": "hi-hat",
        "onset_time_seconds": 44.5,
        "midi_pitch": 42,
        "note_head_type": "x",
        "staff_position": "F#3",
        "display_name": "Hi-Hat (Closed)"
    },
    {
        "drum_type": "hi-hat",
        "onset_time_seconds": 44.7,
        "midi_pitch": 42,
        "note_head_type": "x",
        "staff_position": "F#3",
        "display_name": "Hi-Hat (Closed)"
    },
    {
        "drum_type": "hi-hat",
        "onset_time_seconds": 44.8,
        "midi_pitch": 42,
        "note_head_type": "x",
        "staff_position": "F#3",
        "display_name": "Hi-Hat (Closed)"
    },
    {
        "drum_type": "hi-hat",
        "onset_time_seconds": 44.9,
        "midi_pitch": 42,
        "note_head_type": "x",
        "staff_position": "F#3",
        "display_name": "Hi-Hat (Closed)"
    },
    {
        "drum_type": "hi-hat",
        "onset_time_seconds": 45.0,
        "midi_pitch": 42,
        "note_head_type": "x",
        "staff_position": "F#3",
        "display_name": "Hi-Hat (Closed)"
    },
    {
        "drum_type": "hi-hat",
        "onset_time_seconds": 45.1,
        "midi_pitch": 42,
        "note_head_type": "x",
        "staff_position": "F#3",
        "display_name": "Hi-Hat (Closed)"
    },
    {
        "drum_type": "snare",
        "onset_time_seconds": 45.2,
        "midi_pitch": 38,
        "note_head_type": "normal",
        "staff_position": "C3",
        "display_name": "Snare Drum"
    },
    {
        "drum_type": "snare",
        "onset_time_seconds": 45.3,
        "midi_pitch": 38,
        "note_head_type": "normal",
        "staff_position": "C3",
        "display_name": "Snare Drum"
    },
    {
        "drum_type": "snare",
        "onset_time_seconds": 45.4,
        "midi_pitch": 38,
        "note_head_type": "normal",
        "staff_position": "C3",
        "display_name": "Snare Drum"
    },
    {
        "drum_type": "snare",
        "onset_time_seconds": 45.5,
        "midi_pitch": 38,
        "note_head_type": "normal",
        "staff_position": "C3",
        "display_name": "Snare Drum"
    },
    {
        "drum_type": "hi-hat",
        "onset_time_seconds": 45.7,
        "midi_pitch": 42,
        "note_head_type": "x",
        "staff_position": "F#3",
        "display_name": "Hi-Hat (Closed)"
    },
    {
        "drum_type": "kick",
        "onset_time_seconds": 45.8,
        "midi_pitch": 36,
        "note_head_type": "normal",
        "staff_position": "F2",
        "display_name": "Bass Drum"
    },
    {
        "drum_type": "hi-hat",
        "onset_time_seconds": 46.0,
        "midi_pitch": 42,
        "note_head_type": "x",
        "staff_position": "F#3",
        "display_name": "Hi-Hat (Closed)"
    },
    {
        "drum_type": "kick",
        "onset_time_seconds": 46.1,
        "midi_pitch": 36,
        "note_head_type": "normal",
        "staff_position": "F2",
        "display_name": "Bass Drum"
    },
    {
        "drum_type": "hi-hat",
        "onset_time_seconds": 46.2,
        "midi_pitch": 42,
        "note_head_type": "x",
        "staff_position": "F#3",
        "display_name": "Hi-Hat (Closed)"
    },
    {
        "drum_type": "snare",
        "onset_time_seconds": 46.4,
        "midi_pitch": 38,
        "note_head_type": "normal",
        "staff_position": "C3",
        "display_name": "Snare Drum"
    },
    {
        "drum_type": "hi-hat",
        "onset_time_seconds": 46.5,
        "midi_pitch": 42,
        "note_head_type": "x",
        "staff_position": "F#3",
        "display_name": "Hi-Hat (Closed)"
    },
    {
        "drum_type": "hi-hat",
        "onset_time_seconds": 46.6,
        "midi_pitch": 42,
        "note_head_type": "x",
        "staff_position": "F#3",
        "display_name": "Hi-Hat (Closed)"
    },
    {
        "drum_type": "hi-hat",
        "onset_time_seconds": 46.7,
        "midi_pitch": 42,
        "note_head_type": "x",
        "staff_position": "F#3",
        "display_name": "Hi-Hat (Closed)"
    },
    {
        "drum_type": "hi-hat",
        "onset_time_seconds": 46.8,
        "midi_pitch": 42,
        "note_head_type": "x",
        "staff_position": "F#3",
        "display_name": "Hi-Hat (Closed)"
    },
    {
        "drum_type": "hi-hat",
        "onset_time_seconds": 46.9,
        "midi_pitch": 42,
        "note_head_type": "x",
        "staff_position": "F#3",
        "display_name": "Hi-Hat (Closed)"
    },
    {
        "drum_type": "hi-hat",
        "onset_time_seconds": 47.0,
        "midi_pitch": 42,
        "note_head_type": "x",
        "staff_position": "F#3",
        "display_name": "Hi-Hat (Closed)"
    },
    {
        "drum_type": "snare",
        "onset_time_seconds": 47.1,
        "midi_pitch": 38,
        "note_head_type": "normal",
        "staff_position": "C3",
        "display_name": "Snare Drum"
    },
    {
        "drum_type": "hi-hat",
        "onset_time_seconds": 47.4,
        "midi_pitch": 42,
        "note_head_type": "x",
        "staff_position": "F#3",
        "display_name": "Hi-Hat (Closed)"
    },
    {
        "drum_type": "hi-hat",
        "onset_time_seconds": 47.5,
        "midi_pitch": 42,
        "note_head_type": "x",
        "staff_position": "F#3",
        "display_name": "Hi-Hat (Closed)"
    },
    {
        "drum_type": "hi-hat",
        "onset_time_seconds": 47.6,
        "midi_pitch": 42,
        "note_head_type": "x",
        "staff_position": "F#3",
        "display_name": "Hi-Hat (Closed)"
    },
    {
        "drum_type": "hi-hat",
        "onset_time_seconds": 47.7,
        "midi_pitch": 42,
        "note_head_type": "x",
        "staff_position": "F#3",
        "display_name": "Hi-Hat (Closed)"
    },
    {
        "drum_type": "hi-hat",
        "onset_time_seconds": 47.8,
        "midi_pitch": 42,
        "note_head_type": "x",
        "staff_position": "F#3",
        "display_name": "Hi-Hat (Closed)"
    },
    {
        "drum_type": "kick",
        "onset_time_seconds": 47.9,
        "midi_pitch": 36,
        "note_head_type": "normal",
        "staff_position": "F2",
        "display_name": "Bass Drum"
    },
    {
        "drum_type": "hi-hat",
        "onset_time_seconds": 48.1,
        "midi_pitch": 42,
        "note_head_type": "x",
        "staff_position": "F#3",
        "display_name": "Hi-Hat (Closed)"
    },
    {
        "drum_type": "hi-hat",
        "onset_time_seconds": 48.2,
        "midi_pitch": 42,
        "note_head_type": "x",
        "staff_position": "F#3",
        "display_name": "Hi-Hat (Closed)"
    },
    {
        "drum_type": "snare",
        "onset_time_seconds": 48.3,
        "midi_pitch": 38,
        "note_head_type": "normal",
        "staff_position": "C3",
        "display_name": "Snare Drum"
    },
    {
        "drum_type": "hi-hat",
        "onset_time_seconds": 48.4,
        "midi_pitch": 42,
        "note_head_type": "x",
        "staff_position": "F#3",
        "display_name": "Hi-Hat (Closed)"
    },
    {
        "drum_type": "hi-hat",
        "onset_time_seconds": 48.5,
        "midi_pitch": 42,
        "note_head_type": "x",
        "staff_position": "F#3",
        "display_name": "Hi-Hat (Closed)"
    },
    {
        "drum_type": "hi-hat",
        "onset_time_seconds": 48.6,
        "midi_pitch": 42,
        "note_head_type": "x",
        "staff_position": "F#3",
        "display_name": "Hi-Hat (Closed)"
    },
    {
        "drum_type": "hi-hat",
        "onset_time_seconds": 48.7,
        "midi_pitch": 42,
        "note_head_type": "x",
        "staff_position": "F#3",
        "display_name": "Hi-Hat (Closed)"
    },
    {
        "drum_type": "snare",
        "onset_time_seconds": 48.8,
        "midi_pitch": 38,
        "note_head_type": "normal",
        "staff_position": "C3",
        "display_name": "Snare Drum"
    },
    {
        "drum_type": "snare",
        "onset_time_seconds": 48.9,
        "midi_pitch": 38,
        "note_head_type": "normal",
        "staff_position": "C3",
        "display_name": "Snare Drum"
    },
    {
        "drum_type": "snare",
        "onset_time_seconds": 49.0,
        "midi_pitch": 38,
        "note_head_type": "normal",
        "staff_position": "C3",
        "display_name": "Snare Drum"
    },
    {
        "drum_type": "snare",
        "onset_time_seconds": 49.1,
        "midi_pitch": 38,
        "note_head_type": "normal",
        "staff_position": "C3",
        "display_name": "Snare Drum"
    },
    {
        "drum_type": "snare",
        "onset_time_seconds": 49.2,
        "midi_pitch": 38,
        "note_head_type": "normal",
        "staff_position": "C3",
        "display_name": "Snare Drum"
    },
    {
        "drum_type": "hi-hat",
        "onset_time_seconds": 49.4,
        "midi_pitch": 42,
        "note_head_type": "x",
        "staff_position": "F#3",
        "display_name": "Hi-Hat (Closed)"
    },
    {
        "drum_type": "kick",
        "onset_time_seconds": 49.5,
        "midi_pitch": 36,
        "note_head_type": "normal",
        "staff_position": "F2",
        "display_name": "Bass Drum"
    },
    {
        "drum_type": "hi-hat",
        "onset_time_seconds": 49.7,
        "midi_pitch": 42,
        "note_head_type": "x",
        "staff_position": "F#3",
        "display_name": "Hi-Hat (Closed)"
    },
    {
        "drum_type": "hi-hat",
        "onset_time_seconds": 49.9,
        "midi_pitch": 42,
        "note_head_type": "x",
        "staff_position": "F#3",
        "display_name": "Hi-Hat (Closed)"
    },
    {
        "drum_type": "hi-hat",
        "onset_time_seconds": 50.0,
        "midi_pitch": 42,
        "note_head_type": "x",
        "staff_position": "F#3",
        "display_name": "Hi-Hat (Closed)"
    },
    {
        "drum_type": "hi-hat",
        "onset_time_seconds": 50.1,
        "midi_pitch": 42,
        "note_head_type": "x",
        "staff_position": "F#3",
        "display_name": "Hi-Hat (Closed)"
    },
    {
        "drum_type": "hi-hat",
        "onset_time_seconds": 50.2,
        "midi_pitch": 42,
        "note_head_type": "x",
        "staff_position": "F#3",
        "display_name": "Hi-Hat (Closed)"
    },
    {
        "drum_type": "hi-hat",
        "onset_time_seconds": 50.3,
        "midi_pitch": 42,
        "note_head_type": "x",
        "staff_position": "F#3",
        "display_name": "Hi-Hat (Closed)"
    },
    {
        "drum_type": "hi-hat",
        "onset_time_seconds": 50.4,
        "midi_pitch": 42,
        "note_head_type": "x",
        "staff_position": "F#3",
        "display_name": "Hi-Hat (Closed)"
    },
    {
        "drum_type": "hi-hat",
        "onset_time_seconds": 50.7,
        "midi_pitch": 42,
        "note_head_type": "x",
        "staff_position": "F#3",
        "display_name": "Hi-Hat (Closed)"
    },
    {
        "drum_type": "snare",
        "onset_time_seconds": 50.8,
        "midi_pitch": 38,
        "note_head_type": "normal",
        "staff_position": "C3",
        "display_name": "Snare Drum"
    },
    {
        "drum_type": "hi-hat",
        "onset_time_seconds": 51.1,
        "midi_pitch": 42,
        "note_head_type": "x",
        "staff_position": "F#3",
        "display_name": "Hi-Hat (Closed)"
    },
    {
        "drum_type": "hi-hat",
        "onset_time_seconds": 51.3,
        "midi_pitch": 42,
        "note_head_type": "x",
        "staff_position": "F#3",
        "display_name": "Hi-Hat (Closed)"
    },
    {
        "drum_type": "hi-hat",
        "onset_time_seconds": 51.4,
        "midi_pitch": 42,
        "note_head_type": "x",
        "staff_position": "F#3",
        "display_name": "Hi-Hat (Closed)"
    },
    {
        "drum_type": "hi-hat",
        "onset_time_seconds": 51.5,
        "midi_pitch": 42,
        "note_head_type": "x",
        "staff_position": "F#3",
        "display_name": "Hi-Hat (Closed)"
    },
    {
        "drum_type": "hi-hat",
        "onset_time_seconds": 51.7,
        "midi_pitch": 42,
        "note_head_type": "x",
        "staff_position": "F#3",
        "display_name": "Hi-Hat (Closed)"
    },
    {
        "drum_type": "snare",
        "onset_time_seconds": 51.9,
        "midi_pitch": 38,
        "note_head_type": "normal",
        "staff_position": "C3",
        "display_name": "Snare Drum"
    },
    {
        "drum_type": "snare",
        "onset_time_seconds": 52.0,
        "midi_pitch": 38,
        "note_head_type": "normal",
        "staff_position": "C3",
        "display_name": "Snare Drum"
    },
    {
        "drum_type": "hi-hat",
        "onset_time_seconds": 52.1,
        "midi_pitch": 42,
        "note_head_type": "x",
        "staff_position": "F#3",
        "display_name": "Hi-Hat (Closed)"
    },
    {
        "drum_type": "hi-hat",
        "onset_time_seconds": 52.2,
        "midi_pitch": 42,
        "note_head_type": "x",
        "staff_position": "F#3",
        "display_name": "Hi-Hat (Closed)"
    },
    {
        "drum_type": "hi-hat",
        "onset_time_seconds": 52.3,
        "midi_pitch": 42,
        "note_head_type": "x",
        "staff_position": "F#3",
        "display_name": "Hi-Hat (Closed)"
    },
    {
        "drum_type": "hi-hat",
        "onset_time_seconds": 52.4,
        "midi_pitch": 42,
        "note_head_type": "x",
        "staff_position": "F#3",
        "display_name": "Hi-Hat (Closed)"
    },
    {
        "drum_type": "snare",
        "onset_time_seconds": 52.5,
        "midi_pitch": 38,
        "note_head_type": "normal",
        "staff_position": "C3",
        "display_name": "Snare Drum"
    },
    {
        "drum_type": "snare",
        "onset_time_seconds": 52.6,
        "midi_pitch": 38,
        "note_head_type": "normal",
        "staff_position": "C3",
        "display_name": "Snare Drum"
    },
    {
        "drum_type": "snare",
        "onset_time_seconds": 52.7,
        "midi_pitch": 38,
        "note_head_type": "normal",
        "staff_position": "C3",
        "display_name": "Snare Drum"
    },
    {
        "drum_type": "snare",
        "onset_time_seconds": 52.8,
        "midi_pitch": 38,
        "note_head_type": "normal",
        "staff_position": "C3",
        "display_name": "Snare Drum"
    },
    {
        "drum_type": "snare",
        "onset_time_seconds": 52.9,
        "midi_pitch": 38,
        "note_head_type": "normal",
        "staff_position": "C3",
        "display_name": "Snare Drum"
    },
    {
        "drum_type": "hi-hat",
        "onset_time_seconds": 53.1,
        "midi_pitch": 42,
        "note_head_type": "x",
        "staff_position": "F#3",
        "display_name": "Hi-Hat (Closed)"
    },
    {
        "drum_type": "hi-hat",
        "onset_time_seconds": 53.2,
        "midi_pitch": 42,
        "note_head_type": "x",
        "staff_position": "F#3",
        "display_name": "Hi-Hat (Closed)"
    },
    {
        "drum_type": "kick",
        "onset_time_seconds": 53.3,
        "midi_pitch": 36,
        "note_head_type": "normal",
        "staff_position": "F2",
        "display_name": "Bass Drum"
    },
    {
        "drum_type": "hi-hat",
        "onset_time_seconds": 53.6,
        "midi_pitch": 42,
        "note_head_type": "x",
        "staff_position": "F#3",
        "display_name": "Hi-Hat (Closed)"
    },
    {
        "drum_type": "hi-hat",
        "onset_time_seconds": 53.7,
        "midi_pitch": 42,
        "note_head_type": "x",
        "staff_position": "F#3",
        "display_name": "Hi-Hat (Closed)"
    },
    {
        "drum_type": "hi-hat",
        "onset_time_seconds": 54.0,
        "midi_pitch": 42,
        "note_head_type": "x",
        "staff_position": "F#3",
        "display_name": "Hi-Hat (Closed)"
    },
    {
        "drum_type": "hi-hat",
        "onset_time_seconds": 54.1,
        "midi_pitch": 42,
        "note_head_type": "x",
        "staff_position": "F#3",
        "display_name": "Hi-Hat (Closed)"
    },
    {
        "drum_type": "hi-hat",
        "onset_time_seconds": 54.2,
        "midi_pitch": 42,
        "note_head_type": "x",
        "staff_position": "F#3",
        "display_name": "Hi-Hat (Closed)"
    },
    {
        "drum_type": "snare",
        "onset_time_seconds": 54.3,
        "midi_pitch": 38,
        "note_head_type": "normal",
        "staff_position": "C3",
        "display_name": "Snare Drum"
    },
    {
        "drum_type": "hi-hat",
        "onset_time_seconds": 54.4,
        "midi_pitch": 42,
        "note_head_type": "x",
        "staff_position": "F#3",
        "display_name": "Hi-Hat (Closed)"
    },
    {
        "drum_type": "snare",
        "onset_time_seconds": 54.5,
        "midi_pitch": 38,
        "note_head_type": "normal",
        "staff_position": "C3",
        "display_name": "Snare Drum"
    },
    {
        "drum_type": "hi-hat",
        "onset_time_seconds": 54.8,
        "midi_pitch": 42,
        "note_head_type": "x",
        "staff_position": "F#3",
        "display_name": "Hi-Hat (Closed)"
    },
    {
        "drum_type": "hi-hat",
        "onset_time_seconds": 54.9,
        "midi_pitch": 42,
        "note_head_type": "x",
        "staff_position": "F#3",
        "display_name": "Hi-Hat (Closed)"
    },
    {
        "drum_type": "hi-hat",
        "onset_time_seconds": 55.0,
        "midi_pitch": 42,
        "note_head_type": "x",
        "staff_position": "F#3",
        "display_name": "Hi-Hat (Closed)"
    },
    {
        "drum_type": "hi-hat",
        "onset_time_seconds": 55.1,
        "midi_pitch": 42,
        "note_head_type": "x",
        "staff_position": "F#3",
        "display_name": "Hi-Hat (Closed)"
    },
    {
        "drum_type": "hi-hat",
        "onset_time_seconds": 55.4,
        "midi_pitch": 42,
        "note_head_type": "x",
        "staff_position": "F#3",
        "display_name": "Hi-Hat (Closed)"
    },
    {
        "drum_type": "hi-hat",
        "onset_time_seconds": 55.5,
        "midi_pitch": 42,
        "note_head_type": "x",
        "staff_position": "F#3",
        "display_name": "Hi-Hat (Closed)"
    },
    {
        "drum_type": "hi-hat",
        "onset_time_seconds": 55.6,
        "midi_pitch": 42,
        "note_head_type": "x",
        "staff_position": "F#3",
        "display_name": "Hi-Hat (Closed)"
    },
    {
        "drum_type": "snare",
        "onset_time_seconds": 55.7,
        "midi_pitch": 38,
        "note_head_type": "normal",
        "staff_position": "C3",
        "display_name": "Snare Drum"
    },
    {
        "drum_type": "hi-hat",
        "onset_time_seconds": 55.8,
        "midi_pitch": 42,
        "note_head_type": "x",
        "staff_position": "F#3",
        "display_name": "Hi-Hat (Closed)"
    },
    {
        "drum_type": "hi-hat",
        "onset_time_seconds": 55.9,
        "midi_pitch": 42,
        "note_head_type": "x",
        "staff_position": "F#3",
        "display_name": "Hi-Hat (Closed)"
    },
    {
        "drum_type": "hi-hat",
        "onset_time_seconds": 56.0,
        "midi_pitch": 42,
        "note_head_type": "x",
        "staff_position": "F#3",
        "display_name": "Hi-Hat (Closed)"
    },
    {
        "drum_type": "hi-hat",
        "onset_time_seconds": 56.1,
        "midi_pitch": 42,
        "note_head_type": "x",
        "staff_position": "F#3",
        "display_name": "Hi-Hat (Closed)"
    },
    {
        "drum_type": "snare",
        "onset_time_seconds": 56.2,
        "midi_pitch": 38,
        "note_head_type": "normal",
        "staff_position": "C3",
        "display_name": "Snare Drum"
    },
    {
        "drum_type": "snare",
        "onset_time_seconds": 56.3,
        "midi_pitch": 38,
        "note_head_type": "normal",
        "staff_position": "C3",
        "display_name": "Snare Drum"
    },
    {
        "drum_type": "snare",
        "onset_time_seconds": 56.5,
        "midi_pitch": 38,
        "note_head_type": "normal",
        "staff_position": "C3",
        "display_name": "Snare Drum"
    },
    {
        "drum_type": "hi-hat",
        "onset_time_seconds": 56.6,
        "midi_pitch": 42,
        "note_head_type": "x",
        "staff_position": "F#3",
        "display_name": "Hi-Hat (Closed)"
    },
    {
        "drum_type": "snare",
        "onset_time_seconds": 56.6,
        "midi_pitch": 38,
        "note_head_type": "normal",
        "staff_position": "C3",
        "display_name": "Snare Drum"
    },
    {
        "drum_type": "hi-hat",
        "onset_time_seconds": 56.7,
        "midi_pitch": 42,
        "note_head_type": "x",
        "staff_position": "F#3",
        "display_name": "Hi-Hat (Closed)"
    },
    {
        "drum_type": "hi-hat",
        "onset_time_seconds": 56.8,
        "midi_pitch": 42,
        "note_head_type": "x",
        "staff_position": "F#3",
        "display_name": "Hi-Hat (Closed)"
    },
    {
        "drum_type": "kick",
        "onset_time_seconds": 56.9,
        "midi_pitch": 36,
        "note_head_type": "normal",
        "staff_position": "F2",
        "display_name": "Bass Drum"
    },
    {
        "drum_type": "hi-hat",
        "onset_time_seconds": 57.1,
        "midi_pitch": 42,
        "note_head_type": "x",
        "staff_position": "F#3",
        "display_name": "Hi-Hat (Closed)"
    },
    {
        "drum_type": "hi-hat",
        "onset_time_seconds": 57.3,
        "midi_pitch": 42,
        "note_head_type": "x",
        "staff_position": "F#3",
        "display_name": "Hi-Hat (Closed)"
    },
    {
        "drum_type": "snare",
        "onset_time_seconds": 57.5,
        "midi_pitch": 38,
        "note_head_type": "normal",
        "staff_position": "C3",
        "display_name": "Snare Drum"
    },
    {
        "drum_type": "hi-hat",
        "onset_time_seconds": 57.6,
        "midi_pitch": 42,
        "note_head_type": "x",
        "staff_position": "F#3",
        "display_name": "Hi-Hat (Closed)"
    },
    {
        "drum_type": "hi-hat",
        "onset_time_seconds": 57.7,
        "midi_pitch": 42,
        "note_head_type": "x",
        "staff_position": "F#3",
        "display_name": "Hi-Hat (Closed)"
    },
    {
        "drum_type": "hi-hat",
        "onset_time_seconds": 57.8,
        "midi_pitch": 42,
        "note_head_type": "x",
        "staff_position": "F#3",
        "display_name": "Hi-Hat (Closed)"
    },
    {
        "drum_type": "snare",
        "onset_time_seconds": 58.1,
        "midi_pitch": 38,
        "note_head_type": "normal",
        "staff_position": "C3",
        "display_name": "Snare Drum"
    },
    {
        "drum_type": "snare",
        "onset_time_seconds": 58.2,
        "midi_pitch": 38,
        "note_head_type": "normal",
        "staff_position": "C3",
        "display_name": "Snare Drum"
    },
    {
        "drum_type": "kick",
        "onset_time_seconds": 58.3,
        "midi_pitch": 36,
        "note_head_type": "normal",
        "staff_position": "F2",
        "display_name": "Bass Drum"
    },
    {
        "drum_type": "hi-hat",
        "onset_time_seconds": 58.5,
        "midi_pitch": 42,
        "note_head_type": "x",
        "staff_position": "F#3",
        "display_name": "Hi-Hat (Closed)"
    },
    {
        "drum_type": "hi-hat",
        "onset_time_seconds": 58.6,
        "midi_pitch": 42,
        "note_head_type": "x",
        "staff_position": "F#3",
        "display_name": "Hi-Hat (Closed)"
    },
    {
        "drum_type": "hi-hat",
        "onset_time_seconds": 58.7,
        "midi_pitch": 42,
        "note_head_type": "x",
        "staff_position": "F#3",
        "display_name": "Hi-Hat (Closed)"
    },
    {
        "drum_type": "hi-hat",
        "onset_time_seconds": 58.8,
        "midi_pitch": 42,
        "note_head_type": "x",
        "staff_position": "F#3",
        "display_name": "Hi-Hat (Closed)"
    }
]